flopsmeter/__init__.py
flopsmeter/flopsmeter.py
flopsmeter-0.1.0.dist-info/licenses/LICENSE
flopsmeter-0.1.0.dist-info/METADATA
flopsmeter-0.1.0.dist-info/WHEEL
flopsmeter-0.1.0.dist-info/top_level.txt
flopsmeter-0.1.0.dist-info/RECORD
