Metadata-Version: 2.4
Name: flopsmeter
Version: 0.1.0
Summary: FLOPs & Complexity Calculator for PyTorch Deep Learning Model
Author-email: Fan Chu Hsu <0526phoenix@gmail.com>
License: MIT
Project-URL: Homepage, https://github.com/0526PHOENIX/flopsmeter
Project-URL: Documentation, https://github.com/0526PHOENIX/flopsmeter/blob/master/README.md
Project-URL: Repository, https://github.com/0526PHOENIX/flopsmeter.git
Keywords: pytorch,cnn,flops,complexity,model-analysis,deep-learning
Classifier: License :: OSI Approved :: MIT License
Classifier: Programming Language :: Python :: 3
Classifier: Operating System :: OS Independent
Classifier: Intended Audience :: Developers
Classifier: Topic :: Scientific/Engineering :: Artificial Intelligence
Requires-Python: >=3.10
License-File: LICENSE
Requires-Dist: torch>=2.2.1
Requires-Dist: numpy>=1.26.4
Dynamic: license-file
